{
  "plugin": "datadog",
  "version": "v1.14.0",
  "homepage": "https://github.com/DataDog/datadog-operator",
  "description": "The datadog kubectl plugin provides useful utilities to operate datadog-agent components\nvia the Datadog Operator and the DatadogAgent CRD.\n",
  "archSrc": {
    "aarch64-darwin": {
      "url": "https://github.com/DataDog/datadog-operator/releases/download/v1.14.0/kubectl-datadog_1.14.0_darwin_arm64.zip",
      "sha256": "fd309f3360fc84d46603ca9cac517bb84a1a5f0c873a170c6b6540a144fd6b64",
      "bin": "kubectl-datadog",
      "files": [
        {
          "from": "kubectl-datadog",
          "to": "."
        },
        {
          "from": "LICENSE",
          "to": "."
        }
      ]
    },
    "aarch64-linux": {
      "url": "https://github.com/DataDog/datadog-operator/releases/download/v1.14.0/kubectl-datadog_1.14.0_linux_arm64.zip",
      "sha256": "9b93f01a4066ef8da68c61e428dfb30e8c7eb2e15fc95a47134136613e0462d5",
      "bin": "kubectl-datadog",
      "files": [
        {
          "from": "kubectl-datadog",
          "to": "."
        },
        {
          "from": "LICENSE",
          "to": "."
        }
      ]
    },
    "x86_64-darwin": {
      "url": "https://github.com/DataDog/datadog-operator/releases/download/v1.14.0/kubectl-datadog_1.14.0_darwin_amd64.zip",
      "sha256": "291914e5059afeb2268fedef6a8e54c4df359eeb321f3fb570539c44e91b594c",
      "bin": "kubectl-datadog",
      "files": [
        {
          "from": "kubectl-datadog",
          "to": "."
        },
        {
          "from": "LICENSE",
          "to": "."
        }
      ]
    },
    "x86_64-linux": {
      "url": "https://github.com/DataDog/datadog-operator/releases/download/v1.14.0/kubectl-datadog_1.14.0_linux_amd64.zip",
      "sha256": "b6223dffd59ad3cd9fc89ef01b3ccbfdfe377e3f449c70a43ef860f1cde3c0d4",
      "bin": "kubectl-datadog",
      "files": [
        {
          "from": "kubectl-datadog",
          "to": "."
        },
        {
          "from": "LICENSE",
          "to": "."
        }
      ]
    }
  }
}
