{
  "plugin": "virt",
  "version": "v1.5.2",
  "homepage": "https://github.com/kubevirt/kubectl-virt-plugin",
  "description": "virt plugin is a wrapper for virtctl originating from the KubeVirt project. KubeVirt is a virtualization add-on to\nKubernetes, i.e. it enables to run existing virtual machines on Kubernetes clusters. virtctl controls virtual\nmachine related operations on your Kubernetes cluster like connecting to the serial and VNC consoles.\n\nKubevirt documentation:\n  Installation:\n    https://kubevirt.io/user-guide/operations/installation/\n  User Guide:\n    https://kubevirt.io/user-guide/\n  Minikube Quickstart:\n    https://kubevirt.io/quickstart_minikube/\n  Virtctl usage examples:\n    https://kubevirt.io/user-guide/virtual_machines/accessing_virtual_machines/#graphical-and-serial-console-access\n    https://kubevirt.io/user-guide/virtual_machines/service_objects/#expose-virtualmachineinstance-as-a-loadbalancer-service\n    https://kubevirt.io/user-guide/virtual_machines/replicaset/\n",
  "archSrc": {
    "aarch64-darwin": {
      "url": "https://github.com/kubevirt/kubectl-virt-plugin/releases/download/v1.5.2/virtctl-darwin-arm64.tar.gz",
      "sha256": "14fe6c8b94c7fc7d619a89556623b1375f0398eb4d43fd4f9dd9c7994de01a9f",
      "bin": "virtctl",
      "files": [
        {
          "from": "/virtctl/virtctl-darwin-arm64",
          "to": "virtctl"
        },
        {
          "from": "virtctl/LICENSE",
          "to": "."
        }
      ]
    },
    "aarch64-linux": {
      "url": "https://github.com/kubevirt/kubectl-virt-plugin/releases/download/v1.5.2/virtctl-linux-arm64.tar.gz",
      "sha256": "d70b86ac541be2c5cb56f155b22c5374daf2d2949ae2ce3725bcda50b85ca0cd",
      "bin": "virtctl",
      "files": [
        {
          "from": "/virtctl/virtctl-linux-arm64",
          "to": "virtctl"
        },
        {
          "from": "virtctl/LICENSE",
          "to": "."
        }
      ]
    },
    "x86_64-darwin": {
      "url": "https://github.com/kubevirt/kubectl-virt-plugin/releases/download/v1.5.2/virtctl-darwin-amd64.tar.gz",
      "sha256": "707970aa54cb3d8445d71ea756b488eb2066ba21ca26b7570ecaeeb50ec22c23",
      "bin": "virtctl",
      "files": [
        {
          "from": "/virtctl/virtctl-darwin-amd64",
          "to": "virtctl"
        },
        {
          "from": "virtctl/LICENSE",
          "to": "."
        }
      ]
    },
    "x86_64-linux": {
      "url": "https://github.com/kubevirt/kubectl-virt-plugin/releases/download/v1.5.2/virtctl-linux-amd64.tar.gz",
      "sha256": "44a900b1c92de5c74aee26137bfd349bed2a5a694afcb2b2f035928a3ec85621",
      "bin": "virtctl",
      "files": [
        {
          "from": "/virtctl/virtctl-linux-amd64",
          "to": "virtctl"
        },
        {
          "from": "virtctl/LICENSE",
          "to": "."
        }
      ]
    }
  }
}
