{
  "plugin": "commander",
  "version": "v0.4.4",
  "homepage": "https://github.com/schabrolles/kubectl-commander",
  "description": "kube-commander is an interactive menu (based on fzf) that allows you\nto navigate and interact with objects of your Kubernetes cluster.\nIt is possible to quickly preview object configuration in YAML,\nlogs, events but also edite or delete object or enter into pods.\n\n[ctrl-h] inside the plugin to get the list of available key bindings.\n",
  "archSrc": {
    "aarch64-darwin": {
      "url": "https://github.com/schabrolles/kubectl-commander/archive/refs/tags/v0.4.4.tar.gz",
      "sha256": "cd436a7e4bd73a2d8c29d3c32929cc6cde5b1c8cca56791ee3aca637a14a6eba",
      "bin": "kubectl-commander",
      "files": [
        {
          "from": "kubectl-commander-*/kubectl-commander",
          "to": "."
        },
        {
          "from": "kubectl-commander-*/LICENSE",
          "to": "."
        }
      ]
    },
    "aarch64-linux": {
      "url": "https://github.com/schabrolles/kubectl-commander/archive/refs/tags/v0.4.4.tar.gz",
      "sha256": "cd436a7e4bd73a2d8c29d3c32929cc6cde5b1c8cca56791ee3aca637a14a6eba",
      "bin": "kubectl-commander",
      "files": [
        {
          "from": "kubectl-commander-*/kubectl-commander",
          "to": "."
        },
        {
          "from": "kubectl-commander-*/LICENSE",
          "to": "."
        }
      ]
    },
    "x86_64-darwin": {
      "url": "https://github.com/schabrolles/kubectl-commander/archive/refs/tags/v0.4.4.tar.gz",
      "sha256": "cd436a7e4bd73a2d8c29d3c32929cc6cde5b1c8cca56791ee3aca637a14a6eba",
      "bin": "kubectl-commander",
      "files": [
        {
          "from": "kubectl-commander-*/kubectl-commander",
          "to": "."
        },
        {
          "from": "kubectl-commander-*/LICENSE",
          "to": "."
        }
      ]
    },
    "x86_64-linux": {
      "url": "https://github.com/schabrolles/kubectl-commander/archive/refs/tags/v0.4.4.tar.gz",
      "sha256": "cd436a7e4bd73a2d8c29d3c32929cc6cde5b1c8cca56791ee3aca637a14a6eba",
      "bin": "kubectl-commander",
      "files": [
        {
          "from": "kubectl-commander-*/kubectl-commander",
          "to": "."
        },
        {
          "from": "kubectl-commander-*/LICENSE",
          "to": "."
        }
      ]
    }
  }
}
