{
  "plugin": "split-yaml",
  "version": "v0.1.0",
  "homepage": "https://github.com/nathforge/kubectl-split-yaml",
  "description": "Split Kubernetes YAML output into one file per resource, e.g\n`kubectl get deploy -o yaml | kubectl split-yaml -p deployments`\n",
  "archSrc": {
    "aarch64-linux": {
      "url": "https://github.com/nathforge/kubectl-split-yaml/releases/download/v0.1.0/kubectl-split-yaml_0.1.0_linux_arm64.tar.gz",
      "sha256": "9d0a1fe35de704c58a9f0e081412f812755d6ee5464de6b298649a1fed1e8b58",
      "bin": "kubectl-split-yaml",
      "files": [
        {
          "from": "*",
          "to": "."
        }
      ]
    },
    "x86_64-darwin": {
      "url": "https://github.com/nathforge/kubectl-split-yaml/releases/download/v0.1.0/kubectl-split-yaml_0.1.0_darwin_amd64.tar.gz",
      "sha256": "e9e9f462b262c383fff52a85b818a6f33eda0e91ea853fabc6405a4d4f7e9e44",
      "bin": "kubectl-split-yaml",
      "files": [
        {
          "from": "*",
          "to": "."
        }
      ]
    },
    "x86_64-linux": {
      "url": "https://github.com/nathforge/kubectl-split-yaml/releases/download/v0.1.0/kubectl-split-yaml_0.1.0_linux_amd64.tar.gz",
      "sha256": "8fa9cd92c38f745bf22c5415573067bda2955016db9e5bdcec165fc7b6a2e116",
      "bin": "kubectl-split-yaml",
      "files": [
        {
          "from": "*",
          "to": "."
        }
      ]
    }
  }
}
