{
  "plugin": "kubetail",
  "version": "v0.17.0",
  "homepage": "https://github.com/kubetail-org/kubetail",
  "description": "Kubetail is a general-purpose logging tool for Kubernetes, optimized for\ntailing logs across multi-container workloads in real-time. With Kubetail,\nyou can view logs from all the containers in a workload merged into a single,\nchronological timeline, delivered to your browser or terminal.\n",
  "archSrc": {
    "aarch64-darwin": {
      "url": "https://github.com/kubetail-org/kubetail/releases/download/cli%2Fv0.17.0/kubetail-darwin-arm64.tar.gz",
      "sha256": "30bbfd05fb4a96db8714bfca51941b429ee06de6ff8a0879e6a968bd22bf944b",
      "bin": "kubetail",
      "files": [
        {
          "from": "*",
          "to": "."
        }
      ]
    },
    "aarch64-linux": {
      "url": "https://github.com/kubetail-org/kubetail/releases/download/cli%2Fv0.17.0/kubetail-linux-arm64.tar.gz",
      "sha256": "548fb01804874c3e85f1d6885585cfdf6a6aa8cc3a775b041cd8e6ec846e111e",
      "bin": "kubetail",
      "files": [
        {
          "from": "*",
          "to": "."
        }
      ]
    },
    "x86_64-darwin": {
      "url": "https://github.com/kubetail-org/kubetail/releases/download/cli%2Fv0.17.0/kubetail-darwin-amd64.tar.gz",
      "sha256": "300a3dea31991aca5470516381ccaf249c793e0b6fba03787059cd4740afad28",
      "bin": "kubetail",
      "files": [
        {
          "from": "*",
          "to": "."
        }
      ]
    },
    "x86_64-linux": {
      "url": "https://github.com/kubetail-org/kubetail/releases/download/cli%2Fv0.17.0/kubetail-linux-amd64.tar.gz",
      "sha256": "86052a8e747ac3e0d1a9a26ba0979f2b8ac3871fa9ec97746381286eead5f3db",
      "bin": "kubetail",
      "files": [
        {
          "from": "*",
          "to": "."
        }
      ]
    }
  }
}
